Workbook
Name Slicer_Brand: #N/A
Name Slicer_Country: #N/A
Name Slicer_Date: #N/A
Name Slicer_Sales_Channel: #N/A

Sheet EDA_Dataset
A1: Sale_ID | B1: Date | C1: Brand | D1: Shoe_Type | E1: Color | F1: Country | G1: Sales_Channel | H1: Price_USD | I1: Units_Sold | J1: Revenue_USD
A2: S1 | B2: 45985 | C2: Nike | D2: Boots | E2: Blue | F2: UK | G2: Online | H2: 112.4 | I2: 4 | J2: 449.6 | L2: Column Name | M2: Number of Data | N2: Missing Values | O2: Type of Data | P2: Duplicate Data
A3: S2 | B3: 45729 | C3: Skechers | D3: Boots | E3: Grey | F3: USA | G3: Mall | H3: 239.16 | I3: 4 | J3: 956.64 | L3: Sale_ID | M3: =COUNTA(INDEX(Table1.Sales_Data[],0,MATCH(L3,Table1.Sales_Data[#Headers],0))) -> 1006 | N3: =COUNTBLANK(INDEX(Table1.Sales_Data[],0,MATCH(L3,Table1.Sales_Data[#Headers],0))) -> 0 | O3: =IF(TYPE(INDEX(Table1.Sales_Data[],0,MATCH(L3,Table1.Sales_Data[#Headers],0)))=1,"NUMBER", IF(TYPE(INDEX(Table1.Sales_Data[],0,MATCH(L3,Table1.Sales_Data[#Headers],0)))=2,"TEXT", IF(TYPE(INDEX(Table1.Sales_Data[],0,MATCH(L3,Table1.Sales_Data[#Headers],0)))=4,"LOGICAL", IF(TYPE(INDEX(Table1.Sales_Data[],0,MATCH(L3,Table1.Sales_Data[#Headers],0)))=16,"ERROR", "LAINNYA")))) -> TEXT | P3: Use of Conditional Formatting: to identify duplicate data. In this dataset, the Sale_ID column should contain unique values. The results showed that no duplicate data was detected in the Sale_ID.
A4: S3 | B4: 45874 | C4: Nike | D4: Running | E4: White | F4: UK | G4: Mall | H4: 191.04 | I4: 2 | J4: 382.08 | L4: Date | M4: =COUNTA(INDEX(Table1.Sales_Data[],0,MATCH(L4,Table1.Sales_Data[#Headers],0))) -> 1006 | N4: =COUNTBLANK(INDEX(Table1.Sales_Data[],0,MATCH(L4,Table1.Sales_Data[#Headers],0))) -> 0 | O4: =IF(TYPE(INDEX(Table1.Sales_Data[],0,MATCH(L4,Table1.Sales_Data[#Headers],0)))=1,"DATE", IF(TYPE(INDEX(Table1.Sales_Data[],0,MATCH(L4,Table1.Sales_Data[#Headers],0)))=2,"TEXT", IF(TYPE(INDEX(Table1.Sales_Data[],0,MATCH(L4,Table1.Sales_Data[#Headers],0)))=4,"LOGICAL", IF(TYPE(INDEX(Table1.Sales_Data[],0,MATCH(L4,Table1.Sales_Data[#Headers],0)))=16,"ERROR", "LAINNYA")))) -> DATE
A5: S4 | B5: 45966 | C5: New Balance | D5: Casual | E5: Green | F5: UAE | G5: Mall | H5: 161.7 | I5: 1 | J5: 161.7 | L5: Brand | M5: =COUNTA(INDEX(Table1.Sales_Data[],0,MATCH(L5,Table1.Sales_Data[#Headers],0))) -> 1006 | N5: =COUNTBLANK(INDEX(Table1.Sales_Data[],0,MATCH(L5,Table1.Sales_Data[#Headers],0))) -> 0 | O5: =IF(TYPE(INDEX(Table1.Sales_Data[],0,MATCH(L5,Table1.Sales_Data[#Headers],0)))=1,"NUMBER", IF(TYPE(INDEX(Table1.Sales_Data[],0,MATCH(L5,Table1.Sales_Data[#Headers],0)))=2,"TEXT", IF(TYPE(INDEX(Table1.Sales_Data[],0,MATCH(L5,Table1.Sales_Data[#Headers],0)))=4,"LOGICAL", IF(TYPE(INDEX(Table1.Sales_Data[],0,MATCH(L5,Table1.Sales_Data[#Headers],0)))=16,"ERROR", "LAINNYA")))) -> TEXT
A6: S5 | B6: 45937 | C6: Adidas | D6: Formal | E6: Grey | F6: France | G6: Online | H6: 64.32 | I6: 14 | J6: 900.48 | L6: Shoe_Type | M6: =COUNTA(INDEX(Table1.Sales_Data[],0,MATCH(L6,Table1.Sales_Data[#Headers],0))) -> 1006 | N6: =COUNTBLANK(INDEX(Table1.Sales_Data[],0,MATCH(L6,Table1.Sales_Data[#Headers],0))) -> 0 | O6: =IF(TYPE(INDEX(Table1.Sales_Data[],0,MATCH(L6,Table1.Sales_Data[#Headers],0)))=1,"NUMBER", IF(TYPE(INDEX(Table1.Sales_Data[],0,MATCH(L6,Table1.Sales_Data[#Headers],0)))=2,"TEXT", IF(TYPE(INDEX(Table1.Sales_Data[],0,MATCH(L6,Table1.Sales_Data[#Headers],0)))=4,"LOGICAL", IF(TYPE(INDEX(Table1.Sales_Data[],0,MATCH(L6,Table1.Sales_Data[#Headers],0)))=16,"ERROR", "LAINNYA")))) -> TEXT
A7: S6 | B7: 45739 | C7: Puma | D7: Sports | E7: White | F7: UK | G7: Retail Store | H7: 64.32 | I7: 14 | J7: 900.48 | L7: Color | M7: =COUNTA(INDEX(Table1.Sales_Data[],0,MATCH(L7,Table1.Sales_Data[#Headers],0))) -> 1006 | N7: =COUNTBLANK(INDEX(Table1.Sales_Data[],0,MATCH(L7,Table1.Sales_Data[#Headers],0))) -> 0 | O7: =IF(TYPE(INDEX(Table1.Sales_Data[],0,MATCH(L7,Table1.Sales_Data[#Headers],0)))=1,"NUMBER", IF(TYPE(INDEX(Table1.Sales_Data[],0,MATCH(L7,Table1.Sales_Data[#Headers],0)))=2,"TEXT", IF(TYPE(INDEX(Table1.Sales_Data[],0,MATCH(L7,Table1.Sales_Data[#Headers],0)))=4,"LOGICAL", IF(TYPE(INDEX(Table1.Sales_Data[],0,MATCH(L7,Table1.Sales_Data[#Headers],0)))=16,"ERROR", "LAINNYA")))) -> TEXT
A8: S7 | B8: 45710 | C8: Reebok | D8: Running | E8: Blue | F8: Saudi Arabia | G8: Retail Store | H8: 42.78 | I8: 3 | J8: 128.34 | L8: Country | M8: =COUNTA(INDEX(Table1.Sales_Data[],0,MATCH(L8,Table1.Sales_Data[#Headers],0))) -> 1006 | N8: =COUNTBLANK(INDEX(Table1.Sales_Data[],0,MATCH(L8,Table1.Sales_Data[#Headers],0))) -> 0 | O8: =IF(TYPE(INDEX(Table1.Sales_Data[],0,MATCH(L8,Table1.Sales_Data[#Headers],0)))=1,"NUMBER", IF(TYPE(INDEX(Table1.Sales_Data[],0,MATCH(L8,Table1.Sales_Data[#Headers],0)))=2,"TEXT", IF(TYPE(INDEX(Table1.Sales_Data[],0,MATCH(L8,Table1.Sales_Data[#Headers],0)))=4,"LOGICAL", IF(TYPE(INDEX(Table1.Sales_Data[],0,MATCH(L8,Table1.Sales_Data[#Headers],0)))=16,"ERROR", "LAINNYA")))) -> TEXT
A9: S8 | B9: 45967 | C9: Nike | D9: Boots | E9: Red | F9: India | G9: Online | H9: 220.56 | I9: 9 | J9: 1985.04 | L9: Sales_Channel | M9: =COUNTA(INDEX(Table1.Sales_Data[],0,MATCH(L9,Table1.Sales_Data[#Headers],0))) -> 1006 | N9: =COUNTBLANK(INDEX(Table1.Sales_Data[],0,MATCH(L9,Table1.Sales_Data[#Headers],0))) -> 0 | O9: =IF(TYPE(INDEX(Table1.Sales_Data[],0,MATCH(L9,Table1.Sales_Data[#Headers],0)))=1,"NUMBER", IF(TYPE(INDEX(Table1.Sales_Data[],0,MATCH(L9,Table1.Sales_Data[#Headers],0)))=2,"TEXT", IF(TYPE(INDEX(Table1.Sales_Data[],0,MATCH(L9,Table1.Sales_Data[#Headers],0)))=4,"LOGICAL", IF(TYPE(INDEX(Table1.Sales_Data[],0,MATCH(L9,Table1.Sales_Data[#Headers],0)))=16,"ERROR", "LAINNYA")))) -> TEXT
A10: S9 | B10: 45851 | C10: New Balance | D10: Sports | E10: Green | F10: India | G10: Retail Store | H10: 162.25 | I10: 3 | J10: 486.75 | L10: Price_USD | M10: =COUNTA(INDEX(Table1.Sales_Data[],0,MATCH(L10,Table1.Sales_Data[#Headers],0))) -> 1006 | N10: =COUNTBLANK(INDEX(Table1.Sales_Data[],0,MATCH(L10,Table1.Sales_Data[#Headers],0))) -> 0 | O10: =IF(TYPE(INDEX(Table1.Sales_Data[],0,MATCH(L10,Table1.Sales_Data[#Headers],0)))=1,"NUMBER", IF(TYPE(INDEX(Table1.Sales_Data[],0,MATCH(L10,Table1.Sales_Data[#Headers],0)))=2,"TEXT", IF(TYPE(INDEX(Table1.Sales_Data[],0,MATCH(L10,Table1.Sales_Data[#Headers],0)))=4,"LOGICAL", IF(TYPE(INDEX(Table1.Sales_Data[],0,MATCH(L10,Table1.Sales_Data[#Headers],0)))=16,"ERROR", "LAINNYA")))) -> NUMBER
A11: S10 | B11: 45953 | C11: Skechers | D11: Running | E11: Black | F11: UAE | G11: Online | H11: 185.78 | I11: 7 | J11: 1300.46 | L11: Units_Sold | M11: =COUNTA(INDEX(Table1.Sales_Data[],0,MATCH(L11,Table1.Sales_Data[#Headers],0))) -> 1006 | N11: =COUNTBLANK(INDEX(Table1.Sales_Data[],0,MATCH(L11,Table1.Sales_Data[#Headers],0))) -> 0 | O11: =IF(TYPE(INDEX(Table1.Sales_Data[],0,MATCH(L11,Table1.Sales_Data[#Headers],0)))=1,"NUMBER", IF(TYPE(INDEX(Table1.Sales_Data[],0,MATCH(L11,Table1.Sales_Data[#Headers],0)))=2,"TEXT", IF(TYPE(INDEX(Table1.Sales_Data[],0,MATCH(L11,Table1.Sales_Data[#Headers],0)))=4,"LOGICAL", IF(TYPE(INDEX(Table1.Sales_Data[],0,MATCH(L11,Table1.Sales_Data[#Headers],0)))=16,"ERROR", "LAINNYA")))) -> NUMBER
A12: S11 | B12: 45806 | C12: Adidas | D12: Running | E12: Red | F12: France | G12: Retail Store | H12: 34.53 | I12: 3 | J12: 103.59 | L12: Revenue_USD | M12: =COUNTA(INDEX(Table1.Sales_Data[],0,MATCH(L12,Table1.Sales_Data[#Headers],0))) -> 1006 | N12: =COUNTBLANK(INDEX(Table1.Sales_Data[],0,MATCH(L12,Table1.Sales_Data[#Headers],0))) -> 0 | O12: =IF(TYPE(INDEX(Table1.Sales_Data[],0,MATCH(L12,Table1.Sales_Data[#Headers],0)))=1,"NUMBER", IF(TYPE(INDEX(Table1.Sales_Data[],0,MATCH(L12,Table1.Sales_Data[#Headers],0)))=2,"TEXT", IF(TYPE(INDEX(Table1.Sales_Data[],0,MATCH(L12,Table1.Sales_Data[#Headers],0)))=4,"LOGICAL", IF(TYPE(INDEX(Table1.Sales_Data[],0,MATCH(L12,Table1.Sales_Data[#Headers],0)))=16,"ERROR", "LAINNYA")))) -> NUMBER
A13: S12 | B13: 45983 | C13: Adidas | D13: Sports | E13: Blue | F13: UK | G13: Mall | H13: 243.38 | I13: 12 | J13: 2920.56
A14: S13 | B14: 45794 | C14: New Balance | D14: Boots | E14: White | F14: India | G14: Mall | H14: 213.14 | I14: 3 | J14: 639.42
A15: S14 | B15: 45783 | C15: Reebok | D15: Formal | E15: Blue | F15: UAE | G15: Mall | H15: 76.71 | I15: 6 | J15: 460.26
A16: S15 | B16: 45943 | C16: Skechers | D16: Sports | E16: Black | F16: UK | G16: Online | H16: 70 | I16: 8 | J16: 560
A17: S16 | B17: 45819 | C17: Puma | D17: Running | E17: White | F17: India | G17: Mall | H17: 70.35 | I17: 13 | J17: 914.55
A18: S17 | B18: 45819 | C18: Skechers | D18: Formal | E18: Red | F18: UAE | G18: Retail Store | H18: 96.93 | I18: 7 | J18: 678.51
A19: S18 | B19: 45731 | C19: Adidas | D19: Casual | E19: Green | F19: India | G19: Mall | H19: 145.45 | I19: 9 | J19: 1309.05
A20: S19 | B20: 45792 | C20: Reebok | D20: Sneakers | E20: Red | F20: France | G20: Online | H20: 125.03 | I20: 19 | J20: 2375.57
A21: S20 | B21: 45728 | C21: Reebok | D21: Running | E21: Black | F21: Saudi Arabia | G21: Online | H21: 94.07 | I21: 17 | J21: 1599.19
A22: S21 | B22: 45736 | C22: Skechers | D22: Formal | E22: Grey | F22: USA | G22: Retail Store | H22: 164.61 | I22: 6 | J22: 987.66
A23: S22 | B23: 45853 | C23: Reebok | D23: Sneakers | E23: Blue | F23: India | G23: Online | H23: 60.69 | I23: 20 | J23: 1213.8
A24: S23 | B24: 46006 | C24: Skechers | D24: Sneakers | E24: Blue | F24: Saudi Arabia | G24: Mall | H24: 94.27 | I24: 4 | J24: 377.08
... A1007: S1000 | B1007: 45899 | C1007: Puma | D1007: Casual | E1007: Green | F1007: India | G1007: Online | H1007: 128.12 | I1007: 1 | J1007: 128.12

Sheet DASHBOARD
N2: Total Revenue | P2: AVG Revenue | R2: Monthly Growth | T2: Total Transaction | V2: Total Sold (Pcs)
N3: 98831.17 | P3: 8235.9308 | R3: =Pivot_KPI_Monthly_Growth_Table!E20 -> ▲ 2,69% | T3: 70 | V3: 752
B28: Total Sold by Brand and Shoe Type | L28: Monthly Growth Revenue | Q28: Monthly Revenue Trend
D30: =Pivot_Heatmap!B11 -> Boots | E30: =Pivot_Heatmap!C11 -> Casual | F30: =Pivot_Heatmap!D11 -> Formal | G30: =Pivot_Heatmap!E11 -> Running | H30: =Pivot_Heatmap!F11 -> Sneakers | I30: =Pivot_Heatmap!G11 -> Sports
C31: =Pivot_Heatmap!A12 -> Adidas | D31: =Pivot_Heatmap!B12 -> 36 | E31: =Pivot_Heatmap!C12 -> 21 | F31: =Pivot_Heatmap!D12 -> 0 | G31: =Pivot_Heatmap!E12 -> 14 | H31: =Pivot_Heatmap!F12 -> 27 | I31: =Pivot_Heatmap!G12 -> 30
C32: =Pivot_Heatmap!A13 -> New Balance | D32: =Pivot_Heatmap!B13 -> 25 | E32: =Pivot_Heatmap!C13 -> 54 | F32: =Pivot_Heatmap!D13 -> 22 | G32: =Pivot_Heatmap!E13 -> 47 | H32: =Pivot_Heatmap!F13 -> 21 | I32: =Pivot_Heatmap!G13 -> 11
C33: =Pivot_Heatmap!A14 -> Nike | D33: =Pivot_Heatmap!B14 -> 26 | E33: =Pivot_Heatmap!C14 -> 12 | F33: =Pivot_Heatmap!D14 -> 27 | G33: =Pivot_Heatmap!E14 -> 16 | H33: =Pivot_Heatmap!F14 -> 46 | I33: =Pivot_Heatmap!G14 -> 0
C34: =Pivot_Heatmap!A15 -> Puma | D34: =Pivot_Heatmap!B15 -> 7 | E34: =Pivot_Heatmap!C15 -> 11 | F34: =Pivot_Heatmap!D15 -> 40 | G34: =Pivot_Heatmap!E15 -> 0 | H34: =Pivot_Heatmap!F15 -> 25 | I34: =Pivot_Heatmap!G15 -> 7
C35: =Pivot_Heatmap!A16 -> Reebok | D35: =Pivot_Heatmap!B16 -> 16 | E35: =Pivot_Heatmap!C16 -> 51 | F35: =Pivot_Heatmap!D16 -> 22 | G35: =Pivot_Heatmap!E16 -> 0 | H35: =Pivot_Heatmap!F16 -> 17 | I35: =Pivot_Heatmap!G16 -> 24
C36: =Pivot_Heatmap!A17 -> Skechers | D36: =Pivot_Heatmap!B17 -> 12 | E36: =Pivot_Heatmap!C17 -> 17 | F36: =Pivot_Heatmap!D17 -> 21 | G36: =Pivot_Heatmap!E17 -> 11 | H36: =Pivot_Heatmap!F17 -> 36 | I36: =Pivot_Heatmap!G17 -> 0
B39: Total Sold by Shoe Type and Color
D41: =Pivot_Heatmap!K11 -> Black | E41: =Pivot_Heatmap!L11 -> Blue | F41: =Pivot_Heatmap!M11 -> Green | G41: =Pivot_Heatmap!N11 -> Grey | H41: =Pivot_Heatmap!O11 -> Red | I41: =Pivot_Heatmap!P11 -> White | K41: Total
C42: =Pivot_Heatmap!J12 -> Boots | D42: =Pivot_Heatmap!K12 -> 23 | E42: =Pivot_Heatmap!L12 -> 25 | F42: =Pivot_Heatmap!M12 -> 30 | G42: =Pivot_Heatmap!N12 -> 19 | H42: =Pivot_Heatmap!O12 -> 25 | I42: =Pivot_Heatmap!P12 -> 0 | K42: =Pivot_Heatmap!Q12 -> 122
C43: =Pivot_Heatmap!J13 -> Casual | D43: =Pivot_Heatmap!K13 -> 17 | E43: =Pivot_Heatmap!L13 -> 31 | F43: =Pivot_Heatmap!M13 -> 27 | G43: =Pivot_Heatmap!N13 -> 37 | H43: =Pivot_Heatmap!O13 -> 32 | I43: =Pivot_Heatmap!P13 -> 22 | K43: =Pivot_Heatmap!Q13 -> 166
C44: =Pivot_Heatmap!J14 -> Formal | D44: =Pivot_Heatmap!K14 -> 48 | E44: =Pivot_Heatmap!L14 -> 12 | F44: =Pivot_Heatmap!M14 -> 35 | G44: =Pivot_Heatmap!N14 -> 16 | H44: =Pivot_Heatmap!O14 -> 21 | I44: =Pivot_Heatmap!P14 -> 0 | K44: =Pivot_Heatmap!Q14 -> 132
C45: =Pivot_Heatmap!J15 -> Running | D45: =Pivot_Heatmap!K15 -> 14 | E45: =Pivot_Heatmap!L15 -> 15 | F45: =Pivot_Heatmap!M15 -> 41 | G45: =Pivot_Heatmap!N15 -> 16 | H45: =Pivot_Heatmap!O15 -> 1 | I45: =Pivot_Heatmap!P15 -> 1 | K45: =Pivot_Heatmap!Q15 -> 88
C46: =Pivot_Heatmap!J16 -> Sneakers | D46: =Pivot_Heatmap!K16 -> 39 | E46: =Pivot_Heatmap!L16 -> 38 | F46: =Pivot_Heatmap!M16 -> 17 | G46: =Pivot_Heatmap!N16 -> 38 | H46: =Pivot_Heatmap!O16 -> 25 | I46: =Pivot_Heatmap!P16 -> 15 | K46: =Pivot_Heatmap!Q16 -> 172
C47: =Pivot_Heatmap!J17 -> Sports | D47: =Pivot_Heatmap!K17 -> 10 | E47: =Pivot_Heatmap!L17 -> 20 | F47: =Pivot_Heatmap!M17 -> 16 | G47: =Pivot_Heatmap!N17 -> 18 | H47: =Pivot_Heatmap!O17 -> 0 | I47: =Pivot_Heatmap!P17 -> 8 | K47: =Pivot_Heatmap!Q17 -> 72

Sheet Pivot_KPI_Monthly_Growth_Table
B2: Pivot Revenue
B3: Row Labels | C3: Sum of Revenue_USD | D3: MoM(%)
B4: Jan | C4: 102989.92
B5: Feb | C5: 128723.42 | D5: =(C5-C4)/C4 -> 0.24986426
B6: Mar | C6: 118450.74 | D6: =(C6-C5)/C5 -> -0.079804281
B7: Apr | C7: 115753.37 | D7: =(C7-C6)/C6 -> -0.022772082
B8: Mei | C8: 125637.78 | D8: =(C8-C7)/C7 -> 0.085391985
B9: Jun | C9: 126802.88 | D9: =(C9-C8)/C8 -> 0.0092734845
B10: Jul | C10: 140198.13 | D10: =(C10-C9)/C9 -> 0.10563837
B11: Agu | C11: 96240.75 | D11: =(C11-C10)/C10 -> -0.31353756
B12: Sep | C12: 98831.17 | D12: =(C12-C11)/C11 -> 0.026916041
B13: Okt | C13: 146726.46 | D13: =(C13-C12)/C12 -> 0.48461725
B14: Nov | C14: 131542.53 | D14: =(C14-C13)/C13 -> -0.10348461
B15: Des | C15: 127951.48 | D15: =(C15-C14)/C14 -> -0.027299536
B16: Grand Total | C16: 1459848.6
B18: Pivot Dashboard
B19: Row Labels | C19: Sum of Revenue_USD
B20: Sep | C20: 98831.17 | D20: =VLOOKUP(B20,$B$4:$D$15,3,FALSE) -> 0.026916041 | E20: =IF(D20>=0, "▲ "&TEXT(D20,"0,00%"), "▼ "&TEXT(ABS(D20),"0,00%")) -> ▲ 2,69%
B21: Grand Total | C21: 98831.17

Sheet Pivot_Heatmap
A1: Sum of Units_Sold | B1: Type of Shoes | J1: Sum of Units_Sold | K1: Type of Shoes
A2: Brand | B2: Boots | C2: Casual | D2: Formal | E2: Running | F2: Sneakers | G2: Sports | H2: Grand Total | J2: Brand | K2: Black | L2: Blue | M2: Green | N2: Grey | O2: Red | P2: White | Q2: Grand Total
A3: Adidas | B3: 36 | C3: 21 | E3: 14 | F3: 27 | G3: 30 | H3: 128 | J3: Boots | K3: 23 | L3: 25 | M3: 30 | N3: 19 | O3: 25 | Q3: 122
A4: New Balance | B4: 25 | C4: 54 | D4: 22 | E4: 47 | F4: 21 | G4: 11 | H4: 180 | J4: Casual | K4: 17 | L4: 31 | M4: 27 | N4: 37 | O4: 32 | P4: 22 | Q4: 166
A5: Nike | B5: 26 | C5: 12 | D5: 27 | E5: 16 | F5: 46 | H5: 127 | J5: Formal | K5: 48 | L5: 12 | M5: 35 | N5: 16 | O5: 21 | Q5: 132
A6: Puma | B6: 7 | C6: 11 | D6: 40 | F6: 25 | G6: 7 | H6: 90 | J6: Running | K6: 14 | L6: 15 | M6: 41 | N6: 16 | O6: 1 | P6: 1 | Q6: 88
A7: Reebok | B7: 16 | C7: 51 | D7: 22 | F7: 17 | G7: 24 | H7: 130 | J7: Sneakers | K7: 39 | L7: 38 | M7: 17 | N7: 38 | O7: 25 | P7: 15 | Q7: 172
A8: Skechers | B8: 12 | C8: 17 | D8: 21 | E8: 11 | F8: 36 | H8: 97 | J8: Sports | K8: 10 | L8: 20 | M8: 16 | N8: 18 | P8: 8 | Q8: 72
B11: Boots | C11: Casual | D11: Formal | E11: Running | F11: Sneakers | G11: Sports | H11: Total | K11: Black | L11: Blue | M11: Green | N11: Grey | O11: Red | P11: White | Q11: Grand Total
A12: Adidas | B12: =IFERROR(VLOOKUP(A12,$A$3:$G$8,MATCH($B$11,$A$2:$G$2,0),FALSE),0) -> 36 | C12: =IFERROR(VLOOKUP(A12,$A$3:$G$8,MATCH($C$11,$A$2:$G$2,0),FALSE),0) -> 21 | D12: =IFERROR(VLOOKUP(A12,$A$3:$G$8,MATCH($D$11,$A$2:$G$2,0),FALSE),0) -> 0 | E12: =IFERROR(VLOOKUP(A12,$A$3:$G$8,MATCH($E$11,$A$2:$G$2,0),FALSE),0) -> 14 | F12: =IFERROR(VLOOKUP(A12,$A$3:$G$8,MATCH($F$11,$A$2:$G$2,0),FALSE),0) -> 27 | G12: =IFERROR(VLOOKUP(A12,$A$3:$G$8,MATCH($G$11,$A$2:$G$2,0),FALSE),0) -> 30 | H12: =SUM(B12:G12) -> 128 | J12: Boots | K12: =IFERROR(VLOOKUP(J12,$J$3:$Q$8,MATCH($K$11,$J$2:$Q$2,0),FALSE),0) -> 23 | L12: =IFERROR(VLOOKUP(J12,$J$3:$Q$8,MATCH($L$11,$J$2:$Q$2,0),FALSE),0) -> 25 | M12: =IFERROR(VLOOKUP(J12,$J$3:$Q$8,MATCH($M$11,$J$2:$Q$2,0),FALSE),0) -> 30 | N12: =IFERROR(VLOOKUP(J12,$J$3:$Q$8,MATCH($N$11,$J$2:$Q$2,0),FALSE),0) -> 19 | O12: =IFERROR(VLOOKUP(J12,$J$3:$Q$8,MATCH($O$11,$J$2:$Q$2,0),FALSE),0) -> 25 | P12: =IFERROR(VLOOKUP(J12,$J$3:$Q$8,MATCH($P$11,$J$2:$Q$2,0),FALSE),0) -> 0 | Q12: =SUM(K12:P12) -> 122
A13: New Balance | B13: =IFERROR(VLOOKUP(A13,$A$3:$G$8,MATCH($B$11,$A$2:$G$2,0),FALSE),0) -> 25 | C13: =IFERROR(VLOOKUP(A13,$A$3:$G$8,MATCH($C$11,$A$2:$G$2,0),FALSE),0) -> 54 | D13: =IFERROR(VLOOKUP(A13,$A$3:$G$8,MATCH($D$11,$A$2:$G$2,0),FALSE),0) -> 22 | E13: =IFERROR(VLOOKUP(A13,$A$3:$G$8,MATCH($E$11,$A$2:$G$2,0),FALSE),0) -> 47 | F13: =IFERROR(VLOOKUP(A13,$A$3:$G$8,MATCH($F$11,$A$2:$G$2,0),FALSE),0) -> 21 | G13: =IFERROR(VLOOKUP(A13,$A$3:$G$8,MATCH($G$11,$A$2:$G$2,0),FALSE),0) -> 11 | H13: =SUM(B13:G13) -> 180 | J13: Casual | K13: =IFERROR(VLOOKUP(J13,$J$3:$Q$8,MATCH($K$11,$J$2:$Q$2,0),FALSE),0) -> 17 | L13: =IFERROR(VLOOKUP(J13,$J$3:$Q$8,MATCH($L$11,$J$2:$Q$2,0),FALSE),0) -> 31 | M13: =IFERROR(VLOOKUP(J13,$J$3:$Q$8,MATCH($M$11,$J$2:$Q$2,0),FALSE),0) -> 27 | N13: =IFERROR(VLOOKUP(J13,$J$3:$Q$8,MATCH($N$11,$J$2:$Q$2,0),FALSE),0) -> 37 | O13: =IFERROR(VLOOKUP(J13,$J$3:$Q$8,MATCH($O$11,$J$2:$Q$2,0),FALSE),0) -> 32 | P13: =IFERROR(VLOOKUP(J13,$J$3:$Q$8,MATCH($P$11,$J$2:$Q$2,0),FALSE),0) -> 22 | Q13: =SUM(K13:P13) -> 166
A14: Nike | B14: =IFERROR(VLOOKUP(A14,$A$3:$G$8,MATCH($B$11,$A$2:$G$2,0),FALSE),0) -> 26 | C14: =IFERROR(VLOOKUP(A14,$A$3:$G$8,MATCH($C$11,$A$2:$G$2,0),FALSE),0) -> 12 | D14: =IFERROR(VLOOKUP(A14,$A$3:$G$8,MATCH($D$11,$A$2:$G$2,0),FALSE),0) -> 27 | E14: =IFERROR(VLOOKUP(A14,$A$3:$G$8,MATCH($E$11,$A$2:$G$2,0),FALSE),0) -> 16 | F14: =IFERROR(VLOOKUP(A14,$A$3:$G$8,MATCH($F$11,$A$2:$G$2,0),FALSE),0) -> 46 | G14: =IFERROR(VLOOKUP(A14,$A$3:$G$8,MATCH($G$11,$A$2:$G$2,0),FALSE),0) -> 0 | H14: =SUM(B14:G14) -> 127 | J14: Formal | K14: =IFERROR(VLOOKUP(J14,$J$3:$Q$8,MATCH($K$11,$J$2:$Q$2,0),FALSE),0) -> 48 | L14: =IFERROR(VLOOKUP(J14,$J$3:$Q$8,MATCH($L$11,$J$2:$Q$2,0),FALSE),0) -> 12 | M14: =IFERROR(VLOOKUP(J14,$J$3:$Q$8,MATCH($M$11,$J$2:$Q$2,0),FALSE),0) -> 35 | N14: =IFERROR(VLOOKUP(J14,$J$3:$Q$8,MATCH($N$11,$J$2:$Q$2,0),FALSE),0) -> 16 | O14: =IFERROR(VLOOKUP(J14,$J$3:$Q$8,MATCH($O$11,$J$2:$Q$2,0),FALSE),0) -> 21 | P14: =IFERROR(VLOOKUP(J14,$J$3:$Q$8,MATCH($P$11,$J$2:$Q$2,0),FALSE),0) -> 0 | Q14: =SUM(K14:P14) -> 132
A15: Puma | B15: =IFERROR(VLOOKUP(A15,$A$3:$G$8,MATCH($B$11,$A$2:$G$2,0),FALSE),0) -> 7 | C15: =IFERROR(VLOOKUP(A15,$A$3:$G$8,MATCH($C$11,$A$2:$G$2,0),FALSE),0) -> 11 | D15: =IFERROR(VLOOKUP(A15,$A$3:$G$8,MATCH($D$11,$A$2:$G$2,0),FALSE),0) -> 40 | E15: =IFERROR(VLOOKUP(A15,$A$3:$G$8,MATCH($E$11,$A$2:$G$2,0),FALSE),0) -> 0 | F15: =IFERROR(VLOOKUP(A15,$A$3:$G$8,MATCH($F$11,$A$2:$G$2,0),FALSE),0) -> 25 | G15: =IFERROR(VLOOKUP(A15,$A$3:$G$8,MATCH($G$11,$A$2:$G$2,0),FALSE),0) -> 7 | H15: =SUM(B15:G15) -> 90 | J15: Running | K15: =IFERROR(VLOOKUP(J15,$J$3:$Q$8,MATCH($K$11,$J$2:$Q$2,0),FALSE),0) -> 14 | L15: =IFERROR(VLOOKUP(J15,$J$3:$Q$8,MATCH($L$11,$J$2:$Q$2,0),FALSE),0) -> 15 | M15: =IFERROR(VLOOKUP(J15,$J$3:$Q$8,MATCH($M$11,$J$2:$Q$2,0),FALSE),0) -> 41 | N15: =IFERROR(VLOOKUP(J15,$J$3:$Q$8,MATCH($N$11,$J$2:$Q$2,0),FALSE),0) -> 16 | O15: =IFERROR(VLOOKUP(J15,$J$3:$Q$8,MATCH($O$11,$J$2:$Q$2,0),FALSE),0) -> 1 | P15: =IFERROR(VLOOKUP(J15,$J$3:$Q$8,MATCH($P$11,$J$2:$Q$2,0),FALSE),0) -> 1 | Q15: =SUM(K15:P15) -> 88
A16: Reebok | B16: =IFERROR(VLOOKUP(A16,$A$3:$G$8,MATCH($B$11,$A$2:$G$2,0),FALSE),0) -> 16 | C16: =IFERROR(VLOOKUP(A16,$A$3:$G$8,MATCH($C$11,$A$2:$G$2,0),FALSE),0) -> 51 | D16: =IFERROR(VLOOKUP(A16,$A$3:$G$8,MATCH($D$11,$A$2:$G$2,0),FALSE),0) -> 22 | E16: =IFERROR(VLOOKUP(A16,$A$3:$G$8,MATCH($E$11,$A$2:$G$2,0),FALSE),0) -> 0 | F16: =IFERROR(VLOOKUP(A16,$A$3:$G$8,MATCH($F$11,$A$2:$G$2,0),FALSE),0) -> 17 | G16: =IFERROR(VLOOKUP(A16,$A$3:$G$8,MATCH($G$11,$A$2:$G$2,0),FALSE),0) -> 24 | H16: =SUM(B16:G16) -> 130 | J16: Sneakers | K16: =IFERROR(VLOOKUP(J16,$J$3:$Q$8,MATCH($K$11,$J$2:$Q$2,0),FALSE),0) -> 39 | L16: =IFERROR(VLOOKUP(J16,$J$3:$Q$8,MATCH($L$11,$J$2:$Q$2,0),FALSE),0) -> 38 | M16: =IFERROR(VLOOKUP(J16,$J$3:$Q$8,MATCH($M$11,$J$2:$Q$2,0),FALSE),0) -> 17 | N16: =IFERROR(VLOOKUP(J16,$J$3:$Q$8,MATCH($N$11,$J$2:$Q$2,0),FALSE),0) -> 38 | O16: =IFERROR(VLOOKUP(J16,$J$3:$Q$8,MATCH($O$11,$J$2:$Q$2,0),FALSE),0) -> 25 | P16: =IFERROR(VLOOKUP(J16,$J$3:$Q$8,MATCH($P$11,$J$2:$Q$2,0),FALSE),0) -> 15 | Q16: =SUM(K16:P16) -> 172
A17: Skechers | B17: =IFERROR(VLOOKUP(A17,$A$3:$G$8,MATCH($B$11,$A$2:$G$2,0),FALSE),0) -> 12 | C17: =IFERROR(VLOOKUP(A17,$A$3:$G$8,MATCH($C$11,$A$2:$G$2,0),FALSE),0) -> 17 | D17: =IFERROR(VLOOKUP(A17,$A$3:$G$8,MATCH($D$11,$A$2:$G$2,0),FALSE),0) -> 21 | E17: =IFERROR(VLOOKUP(A17,$A$3:$G$8,MATCH($E$11,$A$2:$G$2,0),FALSE),0) -> 11 | F17: =IFERROR(VLOOKUP(A17,$A$3:$G$8,MATCH($F$11,$A$2:$G$2,0),FALSE),0) -> 36 | G17: =IFERROR(VLOOKUP(A17,$A$3:$G$8,MATCH($G$11,$A$2:$G$2,0),FALSE),0) -> 0 | H17: =SUM(B17:G17) -> 97 | J17: Sports | K17: =IFERROR(VLOOKUP(J17,$J$3:$Q$8,MATCH($K$11,$J$2:$Q$2,0),FALSE),0) -> 10 | L17: =IFERROR(VLOOKUP(J17,$J$3:$Q$8,MATCH($L$11,$J$2:$Q$2,0),FALSE),0) -> 20 | M17: =IFERROR(VLOOKUP(J17,$J$3:$Q$8,MATCH($M$11,$J$2:$Q$2,0),FALSE),0) -> 16 | N17: =IFERROR(VLOOKUP(J17,$J$3:$Q$8,MATCH($N$11,$J$2:$Q$2,0),FALSE),0) -> 18 | O17: =IFERROR(VLOOKUP(J17,$J$3:$Q$8,MATCH($O$11,$J$2:$Q$2,0),FALSE),0) -> 0 | P17: =IFERROR(VLOOKUP(J17,$J$3:$Q$8,MATCH($P$11,$J$2:$Q$2,0),FALSE),0) -> 8 | Q17: =SUM(K17:P17) -> 72

Sheet Pivot_Top_Chart_Tables
A3: Row Labels | B3: Sum of Revenue_USD | D3: Row Labels | E3: Sum of Revenue_USD | G3: Row Labels | H3: Sum of Revenue_USD
A4: Puma | B4: 16114.06 | D4: UK | E4: 16214.22 | G4: Online | H4: 19564.77
A5: Reebok | B5: 20113.67 | D5: USA | E5: 16223.72 | G5: Mall | H5: 38410.8
A6: New Balance | B6: 27014.85 | D6: Germany | E6: 21607.72 | G6: Retail Store | H6: 40855.6
A7: Grand Total | B7: 63242.58 | D7: Grand Total | E7: 54045.66 | G7: Grand Total | H7: 98831.17

Sheet Pivot_Contribution_Tabels
B2: Row Labels | C2: Sum of Revenue_USD | E2: Row Labels | F2: Sum of Revenue_USD | H2: Row Labels | I2: Sum of Revenue_USD
B3: Retail Store | C3: 0.4133878 | E3: New Balance | F3: 0.27334342 | H3: Germany | I3: 0.21863264
B4: Mall | C4: 0.38865067 | E4: Reebok | F4: 0.20351545 | H4: USA | I4: 0.1641559
B5: Online | C5: 0.19796153 | E5: Puma | F5: 0.16304633 | H5: UK | I5: 0.16405978
B6: Grand Total | C6: 1 | E6: Adidas | F6: 0.13790214 | H6: Saudi Arabia | I6: 0.14246811
E7: Nike | F7: 0.12713772 | H7: India | I7: 0.12076241
E8: Skechers | F8: 0.095054931 | H8: France | I8: 0.11281158
E9: Grand Total | F9: 1 | H9: UAE | I9: 0.07710958
H10: Grand Total | I10: 1

Sheet Pivot_Chart_Tables
B2: Row Labels | C2: Sum of Revenue_USD | E2: Row Labels | F2: Sum of Revenue_USD | H2: Row Labels | I2: Count of Sale_ID | K2: Row Labels | L2: Sum of Revenue_USD
B3: Jan | C3: 102989.92 | E3: Jan | H3: Online | I3: 19 | K3: Skechers | L3: 9394.39
B4: Feb | C4: 128723.42 | E4: Feb | F4: 0.24986426 | H4: Mall | I4: 25 | K4: Nike | L4: 12565.17
B5: Mar | C5: 118450.74 | E5: Mar | F5: -0.079804281 | H5: Retail Store | I5: 26 | K5: Adidas | L5: 13629.03
B6: Apr | C6: 115753.37 | E6: Apr | F6: -0.022772082 | H6: Grand Total | I6: 70 | K6: Puma | L6: 16114.06
B7: Mei | C7: 125637.78 | E7: Mei | F7: 0.085391985 | K7: Reebok | L7: 20113.67
B8: Jun | C8: 126802.88 | E8: Jun | F8: 0.0092734845 | K8: New Balance | L8: 27014.85
B9: Jul | C9: 140198.13 | E9: Jul | F9: 0.10563837 | K9: Grand Total | L9: 98831.17
B10: Agu | C10: 96240.75 | E10: Agu | F10: -0.31353756
B11: Sep | C11: 98831.17 | E11: Sep | F11: 0.026916041
B12: Okt | C12: 146726.46 | E12: Okt | F12: 0.48461725
B13: Nov | C13: 131542.53 | E13: Nov | F13: -0.10348461
B14: Des | C14: 127951.48 | E14: Des | F14: -0.027299536
B15: Grand Total | C15: 1459848.6 | E15: Grand Total
